{
  "indexes": [
    {
      "collectionGroup": "attempts",
      "queryScope": "COLLECTION",
      "fields": [
        { "fieldPath": "studentId", "order": "ASCENDING" },
        { "fieldPath": "topic", "order": "ASCENDING" },
        { "fieldPath": "createdAt", "order": "DESCENDING" }
      ]
    },
    {
      "collectionGroup": "students",
      "queryScope": "COLLECTION",
      "fields": [
        { "fieldPath": "total", "order": "DESCENDING" },
        { "fieldPath": "name", "order": "ASCENDING" }
      ]
    }
  ],
  "fieldOverrides": []
}

